esupar/__init__.py
esupar/ainu.py
esupar/esupar.py
esupar/hangul.py
esupar/mecab.py
esupar/simplify.py
esupar/tradify.py
esupar/train.py
esupar/supar/__init__.py
esupar/supar/cmds/__init__.py
esupar/supar/cmds/biaffine_dep.py
esupar/supar/cmds/biaffine_sdp.py
esupar/supar/cmds/cmd.py
esupar/supar/cmds/crf2o_dep.py
esupar/supar/cmds/crf_con.py
esupar/supar/cmds/crf_dep.py
esupar/supar/cmds/vi_con.py
esupar/supar/cmds/vi_dep.py
esupar/supar/cmds/vi_sdp.py
esupar/supar/models/__init__.py
esupar/supar/models/const.py
esupar/supar/models/dep.py
esupar/supar/models/model.py
esupar/supar/models/sdp.py
esupar/supar/modules/__init__.py
esupar/supar/modules/affine.py
esupar/supar/modules/dropout.py
esupar/supar/modules/lstm.py
esupar/supar/modules/mlp.py
esupar/supar/modules/pretrained.py
esupar/supar/modules/scalar_mix.py
esupar/supar/modules/transformer.py
esupar/supar/parsers/__init__.py
esupar/supar/parsers/const.py
esupar/supar/parsers/dep.py
esupar/supar/parsers/parser.py
esupar/supar/parsers/sdp.py
esupar/supar/structs/__init__.py
esupar/supar/structs/dist.py
esupar/supar/structs/fn.py
esupar/supar/structs/linearchain.py
esupar/supar/structs/semiring.py
esupar/supar/structs/tree.py
esupar/supar/structs/vi.py
esupar/supar/utils/__init__.py
esupar/supar/utils/common.py
esupar/supar/utils/config.py
esupar/supar/utils/data.py
esupar/supar/utils/embedding.py
esupar/supar/utils/field.py
esupar/supar/utils/fn.py
esupar/supar/utils/logging.py
esupar/supar/utils/metric.py
esupar/supar/utils/parallel.py
esupar/supar/utils/tokenizer.py
esupar/supar/utils/transform.py
esupar/supar/utils/vocab.py
esupar-1.9.0.dist-info/LICENSE.txt
esupar-1.9.0.dist-info/METADATA
esupar-1.9.0.dist-info/WHEEL
esupar-1.9.0.dist-info/entry_points.txt
esupar-1.9.0.dist-info/top_level.txt
esupar-1.9.0.dist-info/RECORD
