Metadata-Version: 2.1
Name: esupar
Version: 1.9.0
Summary: Tokenizer POS-tagger and Dependency-parser with BERT/RoBERTa/DeBERTa models for Japanese and other languages
Home-page: https://github.com/KoichiYasuoka/esupar
Author: Koichi Yasuoka
Author-email: yasuoka@kanji.zinbun.kyoto-u.ac.jp
License: MIT
Project-URL: Source, https://github.com/KoichiYasuoka/esupar
Project-URL: Tracker, https://github.com/KoichiYasuoka/esupar/issues
Keywords: NLP Japanese Korean Chinese Thai Vietnamese English German Serbian Coptic Ainu
Classifier: License :: OSI Approved :: MIT License
Classifier: Programming Language :: Python :: 3
Classifier: Operating System :: OS Independent
Classifier: Natural Language :: Japanese
Classifier: Natural Language :: Korean
Classifier: Natural Language :: Chinese (Simplified)
Classifier: Natural Language :: Chinese (Traditional)
Classifier: Natural Language :: Thai
Classifier: Natural Language :: Vietnamese
Classifier: Natural Language :: English
Classifier: Natural Language :: German
Classifier: Natural Language :: Serbian
Classifier: Topic :: Text Processing :: Linguistic
Requires-Python: >=3.7
License-File: LICENSE.txt
Requires-Dist: deplacy (>=2.1.1)
Requires-Dist: dill (>=0.3.2)
Requires-Dist: nltk (>=3.1)
Requires-Dist: transformers (>=4.41.2)
